pylogforge.py
PyLogForge-1.0.1.dist-info/METADATA
PyLogForge-1.0.1.dist-info/WHEEL
PyLogForge-1.0.1.dist-info/top_level.txt
PyLogForge-1.0.1.dist-info/RECORD
