Metadata-Version: 2.1
Name: PyLogForge
Version: 1.0.1
Summary: Custom Logger Module
Home-page: https://github.com/krash0n/pylogforge
Author: Sebastián M. Cuevas
Author-email: sebastian.cuevas@greatgeek.net
Classifier: License :: OSI Approved :: MIT License
Classifier: Programming Language :: Python :: 3
Classifier: Programming Language :: Python :: 3.6
Classifier: Programming Language :: Python :: 3.7
Classifier: Programming Language :: Python :: 3.8
Classifier: Programming Language :: Python :: 3.9
Classifier: Programming Language :: Python :: 3.10
